{
  "created_at": "Thu May 03 21:10:42 +0000 2012",
  "id": 198157660758081536,
  "id_str": "198157660758081536",
  "text": "RT @comms2point0: Seven deadly sins of communication (via @cipr_uk @allthingsic) http://t.co/Z9SfSwHy #comms #pr",
  "truncated": false,
  "entities": {
    "hashtags": [],
    "symbols": [],
    "user_mentions": [
      {
        "screen_name": "comms2point0",
        "name": "@comms2point0",
        "id": 337042308,
        "id_str": "337042308",
        "indices": [
          3,
          16
        ]
      }
    ],
    "urls": []
  },
  "source": "<a href=\"http://twitter.com/#!/download/ipad\" rel=\"nofollow\">Twitter for iPad</a>",
  "in_reply_to_status_id": null,
  "in_reply_to_status_id_str": null,
  "in_reply_to_user_id": null,
  "in_reply_to_user_id_str": null,
  "in_reply_to_screen_name": null,
  "user": {
    "id": 393578787,
    "id_str": "393578787",
    "name": "Jemma Moran",
    "screen_name": "JemmaMoran",
    "location": "",
    "description": "",
    "url": null,
    "entities": {
      "description": {
        "urls": []
      }
    },
    "protected": false,
    "followers_count": 1667,
    "friends_count": 997,
    "listed_count": 15,
    "created_at": "Tue Oct 18 19:07:41 +0000 2011",
    "favourites_count": 5420,
    "utc_offset": null,
    "time_zone": null,
    "geo_enabled": false,
    "verified": false,
    "statuses_count": 3347,
    "lang": null,
    "contributors_enabled": false,
    "is_translator": false,
    "is_translation_enabled": false,
    "profile_background_color": "ACDED6",
    "profile_background_image_url": "http://abs.twimg.com/images/themes/theme18/bg.gif",
    "profile_background_image_url_https": "https://abs.twimg.com/images/themes/theme18/bg.gif",
    "profile_background_tile": false,
    "profile_image_url": "http://pbs.twimg.com/profile_images/657536813498769408/u7qpZby2_normal.jpg",
    "profile_image_url_https": "https://pbs.twimg.com/profile_images/657536813498769408/u7qpZby2_normal.jpg",
    "profile_banner_url": "https://pbs.twimg.com/profile_banners/393578787/1362938063",
    "profile_link_color": "038543",
    "profile_sidebar_border_color": "EEEEEE",
    "profile_sidebar_fill_color": "F6F6F6",
    "profile_text_color": "333333",
    "profile_use_background_image": true,
    "has_extended_profile": false,
    "default_profile": false,
    "default_profile_image": false,
    "following": false,
    "follow_request_sent": false,
    "notifications": false,
    "translator_type": "none",
    "withheld_in_countries": []
  },
  "geo": null,
  "coordinates": null,
  "place": null,
  "contributors": null,
  "retweeted_status": {
    "created_at": "Thu May 03 19:40:10 +0000 2012",
    "id": 198134877097435137,
    "id_str": "198134877097435137",
    "text": "Seven deadly sins of communication (via @cipr_uk @allthingsic) http://t.co/Z9SfSwHy #comms #pr",
    "truncated": false,
    "entities": {
      "hashtags": [
        {
          "text": "comms",
          "indices": [
            84,
            90
          ]
        },
        {
          "text": "pr",
          "indices": [
            91,
            94
          ]
        }
      ],
      "symbols": [],
      "user_mentions": [
        {
          "screen_name": "AllthingsIC",
          "name": "Rachel Miller, All Things IC",
          "id": 19400168,
          "id_str": "19400168",
          "indices": [
            49,
            61
          ]
        }
      ],
      "urls": [
        {
          "url": "http://t.co/Z9SfSwHy",
          "expanded_url": "http://bit.ly/InLk2e",
          "display_url": "bit.ly/InLk2e",
          "indices": [
            63,
            83
          ]
        }
      ]
    },
    "source": "<a href=\"http://www.hootsuite.com\" rel=\"nofollow\">Hootsuite</a>",
    "in_reply_to_status_id": null,
    "in_reply_to_status_id_str": null,
    "in_reply_to_user_id": null,
    "in_reply_to_user_id_str": null,
    "in_reply_to_screen_name": null,
    "user": {
      "id": 337042308,
      "id_str": "337042308",
      "name": "@comms2point0",
      "screen_name": "comms2point0",
      "location": "United Kingdom",
      "description": "Flying a flag for communications and communicators.\nBespoke training, strategic consultancy, events & mentoring since 2011. Created and owned by @darrencaveney",
      "url": "https://t.co/VWoagl3k9V",
      "entities": {
        "url": {
          "urls": [
            {
              "url": "https://t.co/VWoagl3k9V",
              "expanded_url": "http://www.comms2point0.co.uk",
              "display_url": "comms2point0.co.uk",
              "indices": [
                0,
                23
              ]
            }
          ]
        },
        "description": {
          "urls": []
        }
      },
      "protected": false,
      "followers_count": 16706,
      "friends_count": 7993,
      "listed_count": 771,
      "created_at": "Sun Jul 17 10:38:00 +0000 2011",
      "favourites_count": 20208,
      "utc_offset": null,
      "time_zone": null,
      "geo_enabled": true,
      "verified": false,
      "statuses_count": 106683,
      "lang": null,
      "contributors_enabled": false,
      "is_translator": false,
      "is_translation_enabled": false,
      "profile_background_color": "838485",
      "profile_background_image_url": "http://abs.twimg.com/images/themes/theme1/bg.png",
      "profile_background_image_url_https": "https://abs.twimg.com/images/themes/theme1/bg.png",
      "profile_background_tile": true,
      "profile_image_url": "http://pbs.twimg.com/profile_images/932368516476522497/Yhzr-v8E_normal.jpg",
      "profile_image_url_https": "https://pbs.twimg.com/profile_images/932368516476522497/Yhzr-v8E_normal.jpg",
      "profile_banner_url": "https://pbs.twimg.com/profile_banners/337042308/1540835801",
      "profile_link_color": "0A570F",
      "profile_sidebar_border_color": "C0DEED",
      "profile_sidebar_fill_color": "DDEEF6",
      "profile_text_color": "333333",
      "profile_use_background_image": true,
      "has_extended_profile": false,
      "default_profile": false,
      "default_profile_image": false,
      "following": false,
      "follow_request_sent": false,
      "notifications": false,
      "translator_type": "none",
      "withheld_in_countries": []
    },
    "geo": null,
    "coordinates": null,
    "place": null,
    "contributors": null,
    "is_quote_status": false,
    "retweet_count": 2,
    "favorite_count": 4,
    "favorited": false,
    "retweeted": false,
    "possibly_sensitive": false,
    "lang": "en"
  },
  "is_quote_status": false,
  "retweet_count": 2,
  "favorite_count": 0,
  "favorited": false,
  "retweeted": false,
  "lang": "en"
}