{
  "created_at": "Wed Feb 15 20:12:07 +0000 2017",
  "id": 831959294824288256,
  "id_str": "831959294824288256",
  "text": "RT @wellhungtweet: We pride ourselves on providing fair food. How many of you choose to eat less but better meat? #OrganicHour https://t.co\u2026",
  "truncated": false,
  "entities": {
    "hashtags": [
      {
        "text": "OrganicHour",
        "indices": [
          114,
          126
        ]
      }
    ],
    "symbols": [],
    "user_mentions": [
      {
        "screen_name": "wellhungtweet",
        "name": "Well Hung Meat Co.",
        "id": 336445708,
        "id_str": "336445708",
        "indices": [
          3,
          17
        ]
      }
    ],
    "urls": []
  },
  "source": "<a href=\"http://twitter.com/download/iphone\" rel=\"nofollow\">Twitter for iPhone</a>",
  "in_reply_to_status_id": null,
  "in_reply_to_status_id_str": null,
  "in_reply_to_user_id": null,
  "in_reply_to_user_id_str": null,
  "in_reply_to_screen_name": null,
  "user": {
    "id": 393578787,
    "id_str": "393578787",
    "name": "Jemma Moran",
    "screen_name": "JemmaMoran",
    "location": "",
    "description": "",
    "url": null,
    "entities": {
      "description": {
        "urls": []
      }
    },
    "protected": false,
    "followers_count": 1667,
    "friends_count": 997,
    "listed_count": 15,
    "created_at": "Tue Oct 18 19:07:41 +0000 2011",
    "favourites_count": 5420,
    "utc_offset": null,
    "time_zone": null,
    "geo_enabled": false,
    "verified": false,
    "statuses_count": 3347,
    "lang": null,
    "contributors_enabled": false,
    "is_translator": false,
    "is_translation_enabled": false,
    "profile_background_color": "ACDED6",
    "profile_background_image_url": "http://abs.twimg.com/images/themes/theme18/bg.gif",
    "profile_background_image_url_https": "https://abs.twimg.com/images/themes/theme18/bg.gif",
    "profile_background_tile": false,
    "profile_image_url": "http://pbs.twimg.com/profile_images/657536813498769408/u7qpZby2_normal.jpg",
    "profile_image_url_https": "https://pbs.twimg.com/profile_images/657536813498769408/u7qpZby2_normal.jpg",
    "profile_banner_url": "https://pbs.twimg.com/profile_banners/393578787/1362938063",
    "profile_link_color": "038543",
    "profile_sidebar_border_color": "EEEEEE",
    "profile_sidebar_fill_color": "F6F6F6",
    "profile_text_color": "333333",
    "profile_use_background_image": true,
    "has_extended_profile": false,
    "default_profile": false,
    "default_profile_image": false,
    "following": false,
    "follow_request_sent": false,
    "notifications": false,
    "translator_type": "none",
    "withheld_in_countries": []
  },
  "geo": null,
  "coordinates": null,
  "place": null,
  "contributors": null,
  "retweeted_status": {
    "created_at": "Wed Feb 15 20:10:19 +0000 2017",
    "id": 831958841034153985,
    "id_str": "831958841034153985",
    "text": "We pride ourselves on providing fair food. How many of you choose to eat less but better meat? #OrganicHour https://t.co/SAnxh4l09B",
    "truncated": false,
    "entities": {
      "hashtags": [
        {
          "text": "OrganicHour",
          "indices": [
            95,
            107
          ]
        }
      ],
      "symbols": [],
      "user_mentions": [],
      "urls": [],
      "media": [
        {
          "id": 831958837305290752,
          "id_str": "831958837305290752",
          "indices": [
            108,
            131
          ],
          "media_url": "http://pbs.twimg.com/media/C4u2J5VUMAAR-n_.jpg",
          "media_url_https": "https://pbs.twimg.com/media/C4u2J5VUMAAR-n_.jpg",
          "url": "https://t.co/SAnxh4l09B",
          "display_url": "pic.twitter.com/SAnxh4l09B",
          "expanded_url": "https://twitter.com/wellhungtweet/status/831958841034153985/photo/1",
          "type": "photo",
          "sizes": {
            "thumb": {
              "w": 150,
              "h": 150,
              "resize": "crop"
            },
            "small": {
              "w": 680,
              "h": 453,
              "resize": "fit"
            },
            "medium": {
              "w": 1200,
              "h": 800,
              "resize": "fit"
            },
            "large": {
              "w": 2048,
              "h": 1365,
              "resize": "fit"
            }
          }
        }
      ]
    },
    "extended_entities": {
      "media": [
        {
          "id": 831958837305290752,
          "id_str": "831958837305290752",
          "indices": [
            108,
            131
          ],
          "media_url": "http://pbs.twimg.com/media/C4u2J5VUMAAR-n_.jpg",
          "media_url_https": "https://pbs.twimg.com/media/C4u2J5VUMAAR-n_.jpg",
          "url": "https://t.co/SAnxh4l09B",
          "display_url": "pic.twitter.com/SAnxh4l09B",
          "expanded_url": "https://twitter.com/wellhungtweet/status/831958841034153985/photo/1",
          "type": "photo",
          "sizes": {
            "thumb": {
              "w": 150,
              "h": 150,
              "resize": "crop"
            },
            "small": {
              "w": 680,
              "h": 453,
              "resize": "fit"
            },
            "medium": {
              "w": 1200,
              "h": 800,
              "resize": "fit"
            },
            "large": {
              "w": 2048,
              "h": 1365,
              "resize": "fit"
            }
          }
        }
      ]
    },
    "source": "<a href=\"http://www.hootsuite.com\" rel=\"nofollow\">Hootsuite</a>",
    "in_reply_to_status_id": null,
    "in_reply_to_status_id_str": null,
    "in_reply_to_user_id": null,
    "in_reply_to_user_id_str": null,
    "in_reply_to_screen_name": null,
    "user": {
      "id": 336445708,
      "id_str": "336445708",
      "name": "Well Hung Meat Co.",
      "screen_name": "wellhungtweet",
      "location": "Bratton Clovelly, England",
      "description": "Tender, delicious, dry-aged & hand butchered organic meats - delivered from our fields to your door.",
      "url": "https://t.co/M6bt0ewsxF",
      "entities": {
        "url": {
          "urls": [
            {
              "url": "https://t.co/M6bt0ewsxF",
              "expanded_url": "http://www.wellhungmeat.com",
              "display_url": "wellhungmeat.com",
              "indices": [
                0,
                23
              ]
            }
          ]
        },
        "description": {
          "urls": []
        }
      },
      "protected": false,
      "followers_count": 3967,
      "friends_count": 1170,
      "listed_count": 0,
      "created_at": "Sat Jul 16 09:16:01 +0000 2011",
      "favourites_count": 2039,
      "utc_offset": null,
      "time_zone": null,
      "geo_enabled": true,
      "verified": false,
      "statuses_count": 3269,
      "lang": null,
      "contributors_enabled": false,
      "is_translator": false,
      "is_translation_enabled": false,
      "profile_background_color": "31CC12",
      "profile_background_image_url": "http://abs.twimg.com/images/themes/theme1/bg.png",
      "profile_background_image_url_https": "https://abs.twimg.com/images/themes/theme1/bg.png",
      "profile_background_tile": true,
      "profile_image_url": "http://pbs.twimg.com/profile_images/971048795088793600/vzZWKjXd_normal.jpg",
      "profile_image_url_https": "https://pbs.twimg.com/profile_images/971048795088793600/vzZWKjXd_normal.jpg",
      "profile_banner_url": "https://pbs.twimg.com/profile_banners/336445708/1520596031",
      "profile_link_color": "56987C",
      "profile_sidebar_border_color": "FFFFFF",
      "profile_sidebar_fill_color": "DDEEF6",
      "profile_text_color": "333333",
      "profile_use_background_image": true,
      "has_extended_profile": false,
      "default_profile": false,
      "default_profile_image": false,
      "following": false,
      "follow_request_sent": false,
      "notifications": false,
      "translator_type": "none",
      "withheld_in_countries": []
    },
    "geo": null,
    "coordinates": null,
    "place": null,
    "contributors": null,
    "is_quote_status": false,
    "retweet_count": 1,
    "favorite_count": 7,
    "favorited": false,
    "retweeted": false,
    "possibly_sensitive": false,
    "lang": "en"
  },
  "is_quote_status": false,
  "retweet_count": 1,
  "favorite_count": 0,
  "favorited": false,
  "retweeted": false,
  "lang": "en"
}